{ "items" : [ { "img" : "https://media.suckhoedoisong.vn/thumb_600x400/Images/duylinh/2019/01/26/nhu-co-tich-giua-dai-ngan1548516276.jpg", "head" : "Như cổ tích giữa đại ngàn", "desc" : "Suckhoedoisong.vn - Nhiều khu dân cư ẩn mình trong heo hút đến những làng mạc trải dài theo đường quốc lộ ở Tây Nguyên bừng lên niềm hạnh phúc.", "times" : "41 phút trước", "links" : "https://suckhoedoisong.vn/nhu-co-tich-giua-dai-ngan-n153182.html" },  { "img" : "https://nld.mediacdn.vn/zoom/600_315/2019/2/2/3s0a6209-15490715831401193314232.jpg", "head" : "Clip: Dương Khắc Linh tung nhạc phim Trạng Quỳnh do người yêu Sara Lưu hát", "desc" : "(NLĐO)- Triển khai từ nhạc phim Trạng Quỳnh, ca khúc Duy nhất cho em với phần thể hiện của Sara Lưu thu hút sự chú ý của khán giả ngay cả khi phim chưa ra mắt vì giai điệu da diết và thú vị.", "times" : "36 phút trước", "links" : "http://nld.com.vn/van-nghe/duong-khac-linh-tung-nhac-phim-trang-quynh-do-nguoi-yeu-sara-luu-hat-20190202090304413.htm" },  { "img" : "https://nld.mediacdn.vn/zoom/600_315/2019/2/2/photo-1-15490776964351958843993-crop-15490783930492039260604.jpg", "head" : "Lộ tình tiết hàng loạt nữ sinh Hải Phòng bỗng dưng... mất tích", "desc" : "Ngay tại thời điểm xác minh, Tuấn và một đám thanh niên đang sống tụ tập cùng với con gái anh K. trong một nhà trọ trên địa bàn phường Tràng Minh, quận Kiến An, TP Hải Phòng", "times" : "30 phút trước", "links" : "http://nld.com.vn/ky-an/lo-tinh-tiet-hang-loat-nu-sinh-hai-phong-bong-dung-mat-tich-20190202103654746.htm" },  { "img" : "https://nld.mediacdn.vn/zoom/600_315/2019/2/2/dsc4209-1549077341811209759534.jpg", "head" : "Ngày đầu nghỉ Tết, rút tiền ATM không được, còn bị nuốt thẻ", "desc" : "(NLĐO) – Ngày 2-2, ngày đầu tiên của kỳ nghỉ Tết Nguyên Đán, tình trạng máy ATM trục trặc, nghẽn mạng khiến chủ thẻ không rút được tiền, thậm chí nuốt thẻ, vẫn tiếp tục xảy ra.", "times" : "29 phút trước", "links" : "http://nld.com.vn/kinh-te/ngay-dau-nghi-tet-rut-tien-atm-khong-duoc-con-bi-nuot-the-20190202101904287.htm" },  { "img" : "https://nld.mediacdn.vn/zoom/600_315/2019/1/31/img3986-15489074005831950016208.jpg", "head" : "Làng chài tỉ phú", "desc" : "(NLĐO) -Ở làng chài ấy, hàng trăm gia đình sắm được xe hơi, hàng ngàn hộ xây được nhà lầu và dụng cụ đắt tiền,...", "times" : "22 phút trước", "links" : "http://nld.com.vn/thoi-su/lang-chai-ti-phu-20190131111326303.htm" },  { "img" : "https://nld.mediacdn.vn/zoom/600_315/2019/1/28/img6377-154866300398945264194.jpg", "head" : "Hình hài sách giáo khoa mới của TP HCM ra sao?", "desc" : "(NLĐO)- TP HCM đã chính thức bắt tay vào biên soạn bộ sách giáo khoa mang hình hài, hơi thở riêng của TP, trên cơ sở đáp ứng khung chương trình giáo dục theo quy định của Bộ Giáo dục và Đào tạo (GD-ĐT).", "times" : "31 phút trước", "links" : "http://nld.com.vn/giao-duc-khoa-hoc/hinh-hai-sach-giao-khoa-moi-cua-tp-hcm-ra-sao-20190202101425374.htm" },  { "img" : "https://nld.mediacdn.vn/zoom/600_315/2019/2/2/photo-1-1549078000777220356481.jpg", "head" : "Công ty Mỹ khóc ròng nộp phạt vì mi giả Triều Tiên", "desc" : "(NLĐO)- Trong khoảng thời gian từ 2012-2017, E.L.F. đã nhập khẩu 156 chuyến hàng mi giả từ 2 nhà cung cấp đặt trụ sở ở Trung Quốc chứa các nguyên liệu từ Triều Tiên. Công ty này đối mặt với nguy cơ bị phạt 40 triệu USD.", "times" : "26 phút trước", "links" : "http://nld.com.vn/thoi-su-quoc-te/cong-ty-my-khoc-rong-nop-phat-vi-mi-gia-trieu-tien-20190202103102996.htm" },  { "img" : "https://nld.mediacdn.vn/zoom/600_315/2019/2/2/514151254172684856849212215482467878436864n-15490775742131763232530.jpg", "head" : "Cán bộ điều tra góp tiền cho… tên cướp!", "desc" : "(NLĐO) – Trong quá trình điều tra, thấy hoàn cảnh gia đình đối tượng cướp tài sản quá khó khăn nên các cán bộ điều tra đã góp tiền hỗ trợ.", "times" : "21 phút trước", "links" : "http://nld.com.vn/tin-doc-quyen/can-bo-dieu-tra-gop-tien-cho-ten-cuop-20190202102703895.htm" },  { "img" : "https://image1.ictnews.vn/_Files/2019/01/31/_dsf9249.jpg", "head" : "Cách vệ sinh điện thoại, laptop, tủ lạnh, máy giặt... để đón Tết", "desc" : "ictnews Cùng với hoạt động dọn dẹp nhà cửa ăn Tết, bạn cũng nên dành chút thời gian vệ sinh các thiết bị điện tử để cảm nhận cuộc sống quanh mình thêm tươi mới, khỏe khoắn.", "times" : "17 phút trước", "links" : "https://ictnews.vn/the-gioi-so/cach-ve-sinh-dien-thoai-laptop-tu-lanh-may-giat-de-don-tet-178482.ict" },  { "img" : "https://vnn-imgs-f.vgcloud.vn/2019/02/02/09/sau-gan-20-nam-doan-tuyet-hong-kim-bao-noi-ve-pham-bang-bang-1.jpeg", "head" : "Sau gần 20 năm đoạn tuyệt, Hồng Kim Bảo nói về Phạm Băng Băng", "desc" : "Ngày 31/1, trang Sohu đưa tin Hồng Kim Bảo họp báo công bố bộ phim mới. Dù đã ở tuổi 67, ngôi sao võ thuật Hong Kong vẫn miệt mài đóng phim. Trong buổi họp báo, ông chia sẻ những tin tức về gia đình, sự nghiệp, đồng thời còn thể hiện thái độ liên quan đến Phạm Băng Băng.", "times" : "18 phút trước", "links" : "http://vietnamnet.vn/vn/giai-tri/phim/sau-gan-20-nam-doan-tuyet-hong-kim-bao-noi-ve-pham-bang-bang-506483.html" } ] }