{ "items" : [ { "img" : "https://nld.mediacdn.vn/zoom/600_315/2019/5/14/3-12-2018-sggpo-ongtetridungnafe-1-1557847568396525243529.jpg", "head" : "Bắt tạm giam ông Tề Trí Dũng về hành vi tham ô tài sản", "desc" : "(NLĐO) - Tối 14-5, Công an TP HCM đã thực hiện lệnh bắt tạm giam, khám xét nơi ở của ông Tề Trí Dũng do liên quan đến các sai phạm tại Công ty TNHH MTV phát triển công nghiệp Tân Thuận (IPC).", "times" : "20 giờ trước", "links" : "http://nld.com.vn/phap-luat/phe-chuan-bat-tam-giam-ong-te-tri-dung-tham-o-tai-san-20190514222425659.htm" },  { "img" : "https://nld.mediacdn.vn/zoom/600_315/2019/5/15/d37da3252364ca3a9375-15579119382302118984758.jpg", "head" : "Trung tâm dạy lái xe gắn mác trường thuộc Bộ Công an lừa đảo hơn 450 người", "desc" : "(NLĐO) – Trung tâm đào tạo lái xe gắn mác Trường Đại học PCCC của Bộ Công an cam kết bao đậu rồi lừa đảo hơn 450 người, chiếm đoạt hơn 2 tỉ đồng", "times" : "2 giờ trước", "links" : "http://nld.com.vn/phap-luat/trung-tam-day-lai-xe-gan-mac-truong-thuoc-bo-cong-an-lua-dao-hon-450-nguoi-20190515162514895.htm" },  { "img" : "https://nld.mediacdn.vn/zoom/600_315/2019/5/15/photo-1-15579134665651039944454.jpg", "head" : "Ưu thế quân sự phương Tây đang sụp đổ", "desc" : "(NLĐO) - Ông Michael Haas, chuyên gia tại Trung tâm Nghiên cứu An ninh thuộc Trường Kỹ thuật cao cấp Zurich ở Thụy Sĩ, đã nhận định như vậy trong bài viết đăng trên báo Le Temps gần đây.", "times" : "2 giờ trước", "links" : "http://nld.com.vn/thoi-su-quoc-te/uu-the-quan-su-phuong-tay-dang-sup-do-20190515164954994.htm" },  { "img" : "https://nld.mediacdn.vn/zoom/600_315/2019/5/15/7a4d2e7ee53f0c61552e-1557910797521777368932.jpg", "head" : "Địa điểm và điều kiện học điều dưỡng đa khoa tại Đức với lương học việc 27-34 triệu đồng/tháng", "desc" : "(NLĐO)- Bộ LĐ-TB-XH vừa công bố tiêu chuẩn tuyển 230 học viên điều dưỡng đa khoa tuyển chọn, đào tạo để đưa sang làm việc dài hạn tại Đức mà nếu được tuyển chọn, trong 3 năm đào tạo nghề tại Đức cũng được nhận lương từ 27-34 triệu đồng/tháng.", "times" : "1 giờ trước", "links" : "http://nld.com.vn/cong-doan/dia-diem-va-dieu-kien-hoc-dieu-duong-da-khoa-tai-duc-voi-luong-hoc-viec-27-34-trieu-dong-thang-2019051516252101.htm" },  { "img" : "https://nld.mediacdn.vn/zoom/600_315/2019/5/15/img5346-1557917507532630193391.jpg", "head" : "Ông chủ đội bóng Tottenham chia sẻ lý do chọn đến Cầu Vàng", "desc" : "(NLĐO)- Trong lịch trình du ngoạn tại Đà Nẵng, tỷ phú người Anh Joe Lewis đã có những trải nghiệm thú vị ở Cầu Vàng thuộc Khu du lịch Sun World Ba Na Hills.", "times" : "1 giờ trước", "links" : "http://nld.com.vn/thoi-su/ong-chu-doi-bong-tottenham-chia-se-ly-do-chon-den-cau-vang-20190515175506998.htm" },  { "img" : "https://nld.mediacdn.vn/zoom/600_315/2019/5/15/anhbao-15579179180392015645956.jpg", "head" : "Xe tải tông xe máy, 2 người tử vong", "desc" : "(NLĐO) - Khi đang lưu thông, xe tải bất ngờ tông vào chiếc xe máy đang chạy cùng chiều khiến 2 người ngồi trên xe máy tử vong tại chỗ.", "times" : "1 giờ trước", "links" : "http://nld.com.vn/thoi-su/xe-tai-tong-xe-may-2-nguoi-tu-vong-20190515180008187.htm" },  { "img" : "https://nld.mediacdn.vn/zoom/600_315/2019/5/15/received394362911289634-1557911920980802860359.jpeg", "head" : "Sát hại người tình vì bị không cho ngủ chung", "desc" : "(NLĐO) - Chiều 15-5, Công an tỉnh Tiền Giang cho biết đã khởi tố bị can và bắt tạm giam 4 tháng đối với Phạm Văn Đèo (53 tuổi, ngụ xã Tân Thới, huyện Tân Phú Đông) để điều tra hành vi Giết người", "times" : "1 giờ trước", "links" : "http://nld.com.vn/phap-luat/sat-hai-nguoi-tinh-vi-bi-khong-cho-ngu-chung-20190515161907358.htm" },  { "img" : "https://nld.mediacdn.vn/zoom/600_315/2019/5/15/87700473-1c87-4f4f-9183-85963810d845-1557915420687990699025.jpeg", "head" : "Bị phóng dao trúng ngực, một người tử vong", "desc" : "(NLĐO) - Chỉ mâu thuẫn vụn vặt, đối tượng dùng dao bấm phóng về phía đối phương trúng ngực, khiến nạn nhân tử vong", "times" : "56 phút trước", "links" : "http://nld.com.vn/phap-luat/bi-phong-dao-trung-nguc-mot-nguoi-tu-vong-20190515172652273.htm" },  { "img" : "https://nld.mediacdn.vn/zoom/600_315/2015/exi-1431404653599.jpg", "head" : "Ông Lê Minh Quốc bất ngờ rút đơn kiện HĐQT Eximbank", "desc" : "(NLĐO) - Tòa án Nhân dân TP HCM vừa ban hành quyến định hủy bỏ biện pháp khẩn cấp tạm thời đối với việc Eximbank bầu bà Lương Thị Cẩm Tú làm Chủ tịch Hội đồng quản trị thay cho ông Lê Minh Quốc", "times" : "38 phút trước", "links" : "http://nld.com.vn/kinh-te/ong-le-minh-quoc-bat-ngo-rut-don-kien-hdqt-eximbank-20190515181524595.htm" },  { "img" : "https://image.giaoducthoidai.vn/Uploaded/toannt/2019-05-15/1-FMTO.jpg?width=1000", "head" : "Đội tuyển Việt Nam sẽ khiến Thái Lan bất ngờ ở King's Cup", "desc" : "Dù chỉ là một trận đấu trong khuôn khổ giải đấu giao hữu nhưng đội tuyển Thái Lan nghiên cứu rất kỹ đội tuyển Việt Nam qua băng hình. Khát khao chiến thắng của họ quá lớn, và người hâm mộ Việt Nam chờ HLV Park Hang Seo chơi đòn “dĩ độc trị độc”. ", "times" : "9 giờ trước", "links" : "http://giaoducthoidai.vn/the-thao/doi-tuyen-viet-nam-se-khien-thai-lan-bat-ngo-o-kings-cup-4002938-l.html" } ] }