{ "items" : [ { "img" : "https://congthuong.vn/stores/news_dataimages/hoaquynh/042019/13/15/in_article/croped/0751_2_copy.jpg?randTime=1555148724", "head" : "Báo chí góp phần quan trọng đưa chủ trương, chính sách bảo hiểm xã hội, bảo hiểm y tế đến với doanh nghiệp, người dân", "desc" : "Với độ tin cậy, tính thuyết phục các cơ quan truyền thông, báo chí luôn là người đồng hành, đối tác quan trọng của ngành bảo hiểm xã hội Việt Nam. Đây là khẳng định của ông Đào Việt Ánh – Phó Tổng giám đốc Bảo hiểm xã hội Việt Nam tại Hội nghị Hội nghị tậ", "times" : "1 giờ trước", "links" : "https://congthuong.vn/bao-chi-gop-phan-quan-trong-dua-chu-truong-chinh-sach-bao-hiem-xa-hoi-bao-hiem-y-te-den-voi-doanh-nghiep-nguoi-dan-118347.html" },  { "img" : "//p2.cri.cn/M00/16/C9/CqgNOlyxq-mATiKtAAAAAAAAAAA331.636x365.jpg", "head" : "Nhà lãnh đạo tối cao Triều Tiên Kim Châng Un: Sẵn sàng tổ chức Cuộc gặp thượng đỉnh Triều-Mỹ lần thứ 3 vào lúc điều kiện đầy đủ", "desc" : "Nhà lãnh đạo tối cao Triều Tiên Kim Châng Un: Sẵn sàng tổ chức Cuộc gặp thượng đỉnh Triều-Mỹ lần thứ 3 vào lúc điều kiện đầy đủ", "times" : "1 giờ trước", "links" : "http://vietnamese.cri.cn/20190413/5ab92756-e6a5-2ecf-dfb6-465be077a65f.html" },  { "img" : "//p2.cri.cn/M00/16/CA/CqgNOlyxrRqAbkAsAAAAAAAAAAA264.550x341.jpg", "head" : "Bộ trưởng Tài chính Nhật kêu gọi cảnh giác tình hình căng thẳng mậu dịch có thể leo thang", "desc" : "Bộ trưởng Tài chính Nhật kêu gọi cảnh giác tình hình căng thẳng mậu dịch có thể leo thang", "times" : "1 giờ trước", "links" : "http://vietnamese.cri.cn/20190413/f75b6649-dd06-c082-c360-f57ac2281973.html" },  { "img" : "//p2.cri.cn/M00/16/CB/CqgNOlyxr82ABxBVAAAAAAAAAAA024.960x532.830x460.jpg", "head" : "Thủ tướng TQ Lý Khắc Cường tham dự lễ khai mạc Diễn đàn kinh tế thương mại Trung Quốc-Các nước Trung-Đông Âu lần thứ 9", "desc" : "Thủ tướng TQ Lý Khắc Cường tham dự lễ khai mạc Diễn đàn kinh tế thương mại Trung Quốc-Các nước Trung-Đông Âu lần thứ 9", "times" : "1 giờ trước", "links" : "http://vietnamese.cri.cn/20190413/897f3283-deab-7400-676f-f296272b9bf1.html" },  { "img" : "//p2.cri.cn/M00/16/CA/CqgNOlyxrYiAOmu-AAAAAAAAAAA740.800x534.jpg", "head" : "Khai mạc Hội chợ Giao dịch biên mậu và du lịch Xíp-xoỏng-bản-na lần thứ 22 tại Cảnh Hồng", "desc" : "Khai mạc Hội chợ Giao dịch biên mậu và du lịch Xíp-xoỏng-bản-na lần thứ 22 tại Cảnh Hồng", "times" : "1 giờ trước", "links" : "http://vietnamese.cri.cn/20190413/bba5133d-11fa-3f14-6a45-61f5afc8c94a.html" },  { "img" : "//p2.cri.cn/M00/16/CB/CqgNOlyxr5WALHlQAAAAAAAAAAA551.960x532.830x460.jpg", "head" : "Thủ tướng Trung Quốc Lý Khắc Cường tham dự Cuộc gặp Cấp cao Trung Quốc – Các nước Trung-Đông Âu lần thứ 8", "desc" : "Thủ tướng Trung Quốc Lý Khắc Cường tham dự Cuộc gặp Cấp cao Trung Quốc – Các nước Trung-Đông Âu lần thứ 8", "times" : "1 giờ trước", "links" : "http://vietnamese.cri.cn/20190413/fe3ce2ba-d204-4677-8eaa-9e5e2b1fd6cd.html" },  { "img" : "http://thanhtra.com.vn/portals/0/news_images/2019/04/khaithacanh/52807451_29008025163_loqn.jpg", "head" : "Khởi tố thêm tội Nhận hối lộ với ông Trương Minh Tuấn, Nguyễn Bắc Son", "desc" : "Cơ quan Cảnh sát điều tra Bộ Công an vừa ra Quyết định bổ sung Quyết định khởi tố bị can đối với Nguyễn Bắc Son, Trương Minh Tuấn về tội “Nhận hối lộ”.", "times" : "54 phút trước", "links" : "http://thanhtra.com.vn/tin-tuc-chong-tham-nhung/trong-nuoc/khoi-to-them-toi-nhan-hoi-lo-voi-ong-truong-minh-tuan-nguyen-bac-son_t238c1080n147159" },  { "img" : "https://kenh14cdn.com/zoom/600_315/2019/4/13/567021884115886163384486933436731806973952n-15551465961991439926127-crop-15551466074562137003460.jpg", "head" : "Bắt đại gia Sài Gòn hiếp dâm du học sinh Mỹ", "desc" : "Nguồn tin của phóng viên xác nhận, bị can Nguyễn Phú Cự (là đại gia kinh doanh nhà hàng, quán bar lớn nhất nhì Sài Gòn) cũng là người hiếp dâm 1 du học sinh Mỹ đã vừa bị Phòng Cảnh sát hình sự, Công an TPHCM bắt giữ ở 1 chung cư cao cấp.", "times" : "1 giờ trước", "links" : "http://kenh14.vn/bat-dai-gia-sai-gon-hiep-dam-du-hoc-sinh-my-20190413154037249.chn" },  { "img" : "https://kenh14cdn.com/zoom/600_315/2019/4/13/photo-3-15551419602641715054272-crop-15551423974991111193529.jpg", "head" : "Khám phá những điều bí ẩn của bảo tàng Vault từ thời Liên Xô", "desc" : "Bảo tàng Vault-703 là một công trình kiên cố dưới lòng đất, bắt đầu hoạt động từ năm 1961 như một nơi lưu trữ tài liệu mật của Bộ Ngoại giao Liên Xô.", "times" : "54 phút trước", "links" : "http://kenh14.vn/kham-pha-nhung-dieu-bi-an-cua-bao-tang-vault-tu-thoi-lien-xo-20190413150214296.chn" },  { "img" : "https://kenh14cdn.com/zoom/600_315/2019/4/13/ndn-15551405393851282201621-crop-15551405522561068035802.jpg", "head" : "Mặc tin đồn ngoại tình với Đặng Luân tiếp tục rộ lên, Angela Baby vẫn 1 mình đưa con trai đi chơi cuối tuần", "desc" : "Không có bóng dáng Huỳnh Hiểu Minh, Angela Baby 1 mình chăm sóc cậu con trai quý tử giữa tin đồn ngoại tình.", "times" : "1 giờ trước", "links" : "http://kenh14.vn/mac-tin-don-ngoai-tinh-voi-dang-luan-tiep-tuc-ro-len-angela-baby-van-1-minh-dua-con-trai-di-choi-cuoi-tuan-20190413143034703.chn" } ] }